<concrete5-cif version="1.0">
    <area name="Main">
        <blocks>
            <block type="content" name="" >
                <data table="btContentLocal">
                    <record>
                        <content><![CDATA[
                        <div class="mt-5 mb-5">
                            <h1>Overview</h1>
                            Welcome to the Elemental theme.
                        </div>]]></content>
                    </record>
                </data>
            </block>
        </blocks>
    </area>
</concrete5-cif>
